pyredirect/__init__.py
pyredirect-1.0.0.dist-info/METADATA
pyredirect-1.0.0.dist-info/WHEEL
pyredirect-1.0.0.dist-info/top_level.txt
pyredirect-1.0.0.dist-info/RECORD
