Metadata-Version: 2.1
Name: pyredirect
Version: 1.0.0
Summary: Pyredirect allows you to create redirections by user-agent.
Home-page: https://github.com/lactua/pyredirect
Author: Lactua
Author-email: minedrayxio@gmail.com
Project-URL: Bug Tracker, https://github.com/lactua/pyredirect/issues
Classifier: Programming Language :: Python :: 3
Classifier: License :: OSI Approved :: MIT License
Classifier: Operating System :: OS Independent
Requires-Python: >=3.6
Requires-Dist: requests
